LICENSE
MANIFEST.in
README.rst
setup.cfg
setup.py
drf_react_by_schema/__init__.py
drf_react_by_schema/admin.py
drf_react_by_schema/apps.py
drf_react_by_schema/autocomplete_serializers.py
drf_react_by_schema/autocomplete_viewsets.py
drf_react_by_schema/filters.py
drf_react_by_schema/metadata.py
drf_react_by_schema/models.py
drf_react_by_schema/pagination.py
drf_react_by_schema/renderers.py
drf_react_by_schema/serializers.py
drf_react_by_schema/tests.py
drf_react_by_schema/urls.py
drf_react_by_schema/utils.py
drf_react_by_schema/viewsets.py
drf_react_by_schema.egg-info/PKG-INFO
drf_react_by_schema.egg-info/SOURCES.txt
drf_react_by_schema.egg-info/dependency_links.txt
drf_react_by_schema.egg-info/requires.txt
drf_react_by_schema.egg-info/top_level.txt
drf_react_by_schema/fields/__init__.py
drf_react_by_schema/fields/array.py
drf_react_by_schema/fields/boolean.py
drf_react_by_schema/fields/date.py
drf_react_by_schema/fields/file.py
drf_react_by_schema/fields/number.py
drf_react_by_schema/fields/relational.py
drf_react_by_schema/fields/serializers.py
drf_react_by_schema/fields/text.py
drf_react_by_schema/migrations/__init__.py
drf_react_by_schema/patches/__init__.py
drf_react_by_schema/patches/drf_serializers.py